mad_prefect/data_assets/__init__.py
mad_prefect/data_assets/data_artifact.py
mad_prefect/data_assets/data_artifact_collector.py
mad_prefect/data_assets/data_artifact_query.py
mad_prefect/data_assets/data_asset.py
mad_prefect/data_assets/data_asset_run.py
mad_prefect/data_assets/options.py
mad_prefect/data_assets/utils.py
mad_prefect/duckdb.py
mad_prefect/filesystems.py
mad_prefect/json/mad_json_encoder.py
mad_prefect-2.2.0.dist-info/METADATA
mad_prefect-2.2.0.dist-info/WHEEL
mad_prefect-2.2.0.dist-info/RECORD
