Metadata-Version: 2.3
Name: mad-prefect
Version: 2.2.0
Summary: 
Author: MAIT DEV Pty Ltd
Author-email: maitland@mait.dev
Requires-Python: >=3.11,<3.12
Classifier: Programming Language :: Python :: 3
Classifier: Programming Language :: Python :: 3.11
Requires-Dist: duckdb (>=0.9,<1.3)
Requires-Dist: fsspec (>=2024.9.0,<2025.0.0)
Requires-Dist: jsonlines (>=4.0.0,<5.0.0)
Requires-Dist: pandas (>=2.1.1,<3.0.0)
Requires-Dist: prefect (>=2.18,<3.3)
Requires-Dist: pyarrow (>=16.0.0)
Requires-Dist: sshfs (>=2024.6.0,<2025.0.0)
